MANIFEST.in
requirements.txt
setup.py
amsin/__init__.py
amsin/__main__.py
amsin.egg-info/PKG-INFO
amsin.egg-info/SOURCES.txt
amsin.egg-info/dependency_links.txt
amsin.egg-info/entry_points.txt
amsin.egg-info/requires.txt
amsin.egg-info/top_level.txt