Metadata-Version: 1.0
Name: amsin
Version: 0.1.4
Summary: Simple tool for shortlinking amazon pages.
Home-page: https://github.com/Raynes/amsin
Author: Anthony Grimes
Author-email: i@raynes.me
License: MIT
Platform: UNKNOWN
